{
  "collectionName": "components_blocks_editorial_blocks",
  "info": {
    "displayName": "Editorial Block",
    "icon": "feather"
  },
  "options": {},
  "attributes": {
    "spacingTop": { "type": "string" },
    "spacingBottom": { "type": "string" },
    "rows": { "type": "string" },
    "emphasis": { "type": "string" },
    "appearance": { "type": "string" },
    "textArea": { "type": "string" },
    "headlineSize": { "type": "string" },
    "textAlign": { "type": "string" },
    "textVerticalAlign": { "type": "string" },
    "textInFront": { "type": "boolean" },
    "headline": { "type": "string" },
    "description": { "type": "text" },
    "callToActions": {
      "type": "component",
      "repeatable": true,
      "component": "shared.call-to-action"
    },
    "body": { "type": "text" },
    "ctaText": { "type": "string" },
    "ctaLink": { "type": "string" },
    "imageArea": { "type": "string" },
    "backgroundImageUrl": { "type": "string" },
    "backgroundImagePositionX": { "type": "string" },
    "backgroundImagePositionY": { "type": "string" },
    "imageUrl": { "type": "string" },
    "videoUrl": { "type": "string" },
    "imageFit": { "type": "string" }
  }
}
